<?xml version="1.0" encoding="utf-8"?>
<logs>
  <log>
    <tempretailid>G0001005-3101-20150503133123</tempretailid>
    <depotid>G0001005</depotid>
    <depotname>GRACELAND雅斓嘉兴名店</depotname>
    <instr>document.ocx.DoICBCZJMisTranSTD_Multi("1001", "AMT1=37400", "", "", "", "120400010000")</instr>
    <recodes>
    </recodes>
    <info>
    </info>
    <crname>嘉兴雅斓名店</crname>
    <crdate>2015-05-03 13:32:56:3147 </crdate>
  </log>
  <log>
    <tempretailid>G0001005-3101-20150503133123</tempretailid>
    <depotid>G0001005</depotid>
    <depotname>GRACELAND雅斓嘉兴名店</depotname>
    <instr>document.ocx.DoICBCZJMisTranSTD_Multi("1001", "AMT1=37400", "", "", "", "120400010000")</instr>
    <recodes>004868616678612108   2015050313333500000500000015050310039306000000000003740012045691094210235422400S兴业银行                               银联商户号(UNION PAY MERCHANT CODE):102335056911002
发卡行(ISSUE BANK):兴业银行
总计(TOTAL):RMB 374.00
</recodes>
    <info>交易成功(00)</info>
    <crname>嘉兴雅斓名店</crname>
    <crdate>2015-05-03 13:33:21:5211 </crdate>
  </log>
</logs>