<?xml version="1.0" encoding="utf-8"?>
<logs>
  <log>
    <tempretailid>G0001005-3101-20150421162315</tempretailid>
    <depotid>G0001005</depotid>
    <depotname>GRACELAND雅斓嘉兴名店</depotname>
    <instr>document.ocx.DoICBCZJMisTranSTD_Multi("1001", "AMT1=602300", "", "", "", "120400010000")</instr>
    <recodes>
    </recodes>
    <info>
    </info>
    <crname>嘉兴雅斓名店</crname>
    <crdate>2015-04-21 16:28:52:3182 </crdate>
  </log>
  <log>
    <tempretailid>G0001005-3101-20150421162315</tempretailid>
    <depotid>G0001005</depotid>
    <depotname>GRACELAND雅斓嘉兴名店</depotname>
    <instr>document.ocx.DoICBCZJMisTranSTD_Multi("1001", "AMT1=602300", "", "", "", "120400010000")</instr>
    <recodes>0062220811020028554272015042116293000000500000015042110037875220200000060230012045691094210200000000C牡丹综合账户卡                         银联商户号(UNION PAY MERCHANT CODE):102335056911002
发卡行(ISSUE BANK):中国工商银行
总计(TOTAL):RMB 6023.00
</recodes>
    <info>交易成功(00)</info>
    <crname>嘉兴雅斓名店</crname>
    <crdate>2015-04-21 16:29:17:8857 </crdate>
  </log>
</logs>