<?xml version="1.0" encoding="utf-8"?>
<logs>
  <log>
    <tempretailid>G0001005-3101-20150419164655</tempretailid>
    <depotid>G0001005</depotid>
    <depotname>GRACELAND雅斓嘉兴名店</depotname>
    <instr>document.ocx.DoICBCZJMisTranSTD_Multi("1001", "AMT1=194800", "", "", "", "120400010000")</instr>
    <recodes>
    </recodes>
    <info>
    </info>
    <crname>嘉兴雅斓名店</crname>
    <crdate>2015-04-19 16:47:50:9268 </crdate>
  </log>
  <log>
    <tempretailid>G0001005-3101-20150419164655</tempretailid>
    <depotid>G0001005</depotid>
    <depotname>GRACELAND雅斓嘉兴名店</depotname>
    <instr>document.ocx.DoICBCZJMisTranSTD_Multi("1001", "AMT1=194800", "", "", "", "120400010000")</instr>
    <recodes>006225758308541100   2015041916482900001800000015041910037689200200000019480012045691094210211813000C招商银行                               银联商户号(UNION PAY MERCHANT CODE):102335056911002
发卡行(ISSUE BANK):招商银行
总计(TOTAL):RMB 1948.00
</recodes>
    <info>交易成功(00)</info>
    <crname>嘉兴雅斓名店</crname>
    <crdate>2015-04-19 16:48:21:2955 </crdate>
  </log>
</logs>